.DS_Store
session/__init__.py
pro_tools_session_info-0.1.dist-info/LICENSE
pro_tools_session_info-0.1.dist-info/METADATA
pro_tools_session_info-0.1.dist-info/WHEEL
pro_tools_session_info-0.1.dist-info/top_level.txt
pro_tools_session_info-0.1.dist-info/RECORD
