Metadata-Version: 2.1
Name: pro-tools-session-info
Version: 0.1
Summary: Read Session Info as Text files exported from Avid Pro Tools
Home-page: https://github.com/fantopop/pro-tools-session-info
Author: Ilya Putilin
Author-email: fantopop@gmail.com
License: UNKNOWN
Keywords: audio,daw,edl
Platform: UNKNOWN
Classifier: Programming Language :: Python
Classifier: License :: OSI Approved :: MIT License
Classifier: Operating System :: OS Independent
Classifier: Natural Language :: English
Classifier: Topic :: Multimedia :: Sound/Audio
Classifier: Topic :: Software Development :: Libraries
Requires-Python: >=3.6
Requires-Dist: pandas
Requires-Dist: timecode
